LICENSE.md
MANIFEST.in
README.md
pyproject.toml
setup.cfg
setup.py
pysptk/__init__.py
pysptk/_sptk.pxd
pysptk/_sptk.pyx
pysptk/conversion.py
pysptk/sptk.py
pysptk/synthesis.py
pysptk/util.py
pysptk/example_audio_data/COPYING
pysptk/example_audio_data/arctic_a0007.wav
pysptk_speechify.egg-info/PKG-INFO
pysptk_speechify.egg-info/SOURCES.txt
pysptk_speechify.egg-info/dependency_links.txt
pysptk_speechify.egg-info/requires.txt
pysptk_speechify.egg-info/top_level.txt